{
    "price_comparison": [
        {
            "recommended_item": {
                "item_id": 49269153,
                "name": "LANDSKRONA",
                "price": 8495.0
            },
            "basket_items": [
                {
                    "name": "EKEDALEN / HENRIKSDAL",
                    "price": 4565.0
                },
                {
                    "name": "HAVSTA",
                    "price": 4580.0
                },
                {
                    "name": "LIDHULT",
                    "price": 5428.0
                },
                {
                    "name": "LIDHULT",
                    "price": 7748.0
                }
            ]
        },
        {
            "recommended_item": {
                "item_id": 59256579,
                "name": "GR\u00d6NLID",
                "price": 7400.0
            },
            "basket_items": [
                {
                    "name": "EKEDALEN / HENRIKSDAL",
                    "price": 4565.0
                },
                {
                    "name": "HAVSTA",
                    "price": 4580.0
                },
                {
                    "name": "LIDHULT",
                    "price": 5428.0
                },
                {
                    "name": "LIDHULT",
                    "price": 7748.0
                }
            ]
        },
        {
            "recommended_item": {
                "item_id": 89278612,
                "name": "GR\u00d6NLID",
                "price": 7610.0
            },
            "basket_items": [
                {
                    "name": "EKEDALEN / HENRIKSDAL",
                    "price": 4565.0
                },
                {
                    "name": "HAVSTA",
                    "price": 4580.0
                },
                {
                    "name": "LIDHULT",
                    "price": 5428.0
                },
                {
                    "name": "LIDHULT",
                    "price": 7748.0
                }
            ]
        },
        {
            "recommended_item": {
                "item_id": 89239748,
                "name": "NORSBORG",
                "price": 6780.0
            },
            "basket_items": [
                {
                    "name": "EKEDALEN / HENRIKSDAL",
                    "price": 4565.0
                },
                {
                    "name": "HAVSTA",
                    "price": 4580.0
                },
                {
                    "name": "LIDHULT",
                    "price": 5428.0
                },
                {
                    "name": "LIDHULT",
                    "price": 7748.0
                }
            ]
        },
        {
            "recommended_item": {
                "item_id": 80403154,
                "name": "VEDBO",
                "price": 695.0
            },
            "basket_items": [
                {
                    "name": "EKEDALEN / EKEDALEN",
                    "price": 1245.0
                },
                {
                    "name": "NORDKISA",
                    "price": 476.0
                },
                {
                    "name": "SYVDE",
                    "price": 595.0
                }
            ]
        },
        {
            "recommended_item": {
                "item_id": 40339004,
                "name": "NORR\u00c5KER",
                "price": 595.0
            },
            "basket_items": [
                {
                    "name": "EKEDALEN / EKEDALEN",
                    "price": 1245.0
                },
                {
                    "name": "NORDKISA",
                    "price": 476.0
                },
                {
                    "name": "SYVDE",
                    "price": 595.0
                }
            ]
        },
        {
            "recommended_item": {
                "item_id": 59047147,
                "name": "HILVER / GERTON",
                "price": 665.0
            },
            "basket_items": [
                {
                    "name": "EKEDALEN / EKEDALEN",
                    "price": 1245.0
                },
                {
                    "name": "NORDKISA",
                    "price": 476.0
                },
                {
                    "name": "SYVDE",
                    "price": 595.0
                }
            ]
        },
        {
            "recommended_item": {
                "item_id": 30396655,
                "name": "HEMNES",
                "price": 495.0
            },
            "basket_items": [
                {
                    "name": "EKEDALEN / EKEDALEN",
                    "price": 1245.0
                },
                {
                    "name": "NORDKISA",
                    "price": 476.0
                },
                {
                    "name": "SYVDE",
                    "price": 595.0
                }
            ]
        },
        {
            "recommended_item": {
                "item_id": 59306268,
                "name": "LERHAMN",
                "price": 589.0
            },
            "basket_items": [
                {
                    "name": "EKEDALEN / EKEDALEN",
                    "price": 1245.0
                },
                {
                    "name": "NORDKISA",
                    "price": 476.0
                },
                {
                    "name": "SYVDE",
                    "price": 595.0
                }
            ]
        },
        {
            "recommended_item": {
                "item_id": 40247207,
                "name": "DALSHULT",
                "price": 575.0
            },
            "basket_items": [
                {
                    "name": "EKEDALEN / EKEDALEN",
                    "price": 1245.0
                },
                {
                    "name": "NORDKISA",
                    "price": 476.0
                },
                {
                    "name": "SYVDE",
                    "price": 595.0
                }
            ]
        }
    ],
    "size_comparison": [
        {
            "recommended_item": {
                "item_id": 49269153,
                "name": "LANDSKRONA",
                "size": 4869308.454533055
            },
            "basket_items": [
                {
                    "name": "EKEDALEN / HENRIKSDAL",
                    "size": 2379918.2170087043
                },
                {
                    "name": "HAVSTA",
                    "size": 2411288.0
                },
                {
                    "name": "LIDHULT",
                    "size": 4667112.0
                },
                {
                    "name": "LIDHULT",
                    "size": 6172632.0
                }
            ]
        },
        {
            "recommended_item": {
                "item_id": 59256579,
                "name": "GR\u00d6NLID",
                "size": 4298112.0
            },
            "basket_items": [
                {
                    "name": "EKEDALEN / HENRIKSDAL",
                    "size": 2379918.2170087043
                },
                {
                    "name": "HAVSTA",
                    "size": 2411288.0
                },
                {
                    "name": "LIDHULT",
                    "size": 4667112.0
                },
                {
                    "name": "LIDHULT",
                    "size": 6172632.0
                }
            ]
        },
        {
            "recommended_item": {
                "item_id": 89278612,
                "name": "GR\u00d6NLID",
                "size": 4298112.0
            },
            "basket_items": [
                {
                    "name": "EKEDALEN / HENRIKSDAL",
                    "size": 2379918.2170087043
                },
                {
                    "name": "HAVSTA",
                    "size": 2411288.0
                },
                {
                    "name": "LIDHULT",
                    "size": 4667112.0
                },
                {
                    "name": "LIDHULT",
                    "size": 6172632.0
                }
            ]
        },
        {
            "recommended_item": {
                "item_id": 89239748,
                "name": "NORSBORG",
                "size": 3690757.188522804
            },
            "basket_items": [
                {
                    "name": "EKEDALEN / HENRIKSDAL",
                    "size": 2379918.2170087043
                },
                {
                    "name": "HAVSTA",
                    "size": 2411288.0
                },
                {
                    "name": "LIDHULT",
                    "size": 4667112.0
                },
                {
                    "name": "LIDHULT",
                    "size": 6172632.0
                }
            ]
        },
        {
            "recommended_item": {
                "item_id": 80403154,
                "name": "VEDBO",
                "size": 333060.0
            },
            "basket_items": [
                {
                    "name": "EKEDALEN / EKEDALEN",
                    "size": 789593.7677819963
                },
                {
                    "name": "NORDKISA",
                    "size": 282188.0
                },
                {
                    "name": "SYVDE",
                    "size": 374400.0
                }
            ]
        },
        {
            "recommended_item": {
                "item_id": 40339004,
                "name": "NORR\u00c5KER",
                "size": 370605.0350349502
            },
            "basket_items": [
                {
                    "name": "EKEDALEN / EKEDALEN",
                    "size": 789593.7677819963
                },
                {
                    "name": "NORDKISA",
                    "size": 282188.0
                },
                {
                    "name": "SYVDE",
                    "size": 374400.0
                }
            ]
        },
        {
            "recommended_item": {
                "item_id": 59047147,
                "name": "HILVER / GERTON",
                "size": 322455.0313912505
            },
            "basket_items": [
                {
                    "name": "EKEDALEN / EKEDALEN",
                    "size": 789593.7677819963
                },
                {
                    "name": "NORDKISA",
                    "size": 282188.0
                },
                {
                    "name": "SYVDE",
                    "size": 374400.0
                }
            ]
        },
        {
            "recommended_item": {
                "item_id": 30396655,
                "name": "HEMNES",
                "size": 409664.0
            },
            "basket_items": [
                {
                    "name": "EKEDALEN / EKEDALEN",
                    "size": 789593.7677819963
                },
                {
                    "name": "NORDKISA",
                    "size": 282188.0
                },
                {
                    "name": "SYVDE",
                    "size": 374400.0
                }
            ]
        },
        {
            "recommended_item": {
                "item_id": 59306268,
                "name": "LERHAMN",
                "size": 292603.52745781216
            },
            "basket_items": [
                {
                    "name": "EKEDALEN / EKEDALEN",
                    "size": 789593.7677819963
                },
                {
                    "name": "NORDKISA",
                    "size": 282188.0
                },
                {
                    "name": "SYVDE",
                    "size": 374400.0
                }
            ]
        },
        {
            "recommended_item": {
                "item_id": 40247207,
                "name": "DALSHULT",
                "size": 293242.51292399294
            },
            "basket_items": [
                {
                    "name": "EKEDALEN / EKEDALEN",
                    "size": 789593.7677819963
                },
                {
                    "name": "NORDKISA",
                    "size": 282188.0
                },
                {
                    "name": "SYVDE",
                    "size": 374400.0
                }
            ]
        }
    ],
    "explainable_texts": [
        {
            "recommended_item": {
                "item_id": 49269153,
                "name": "LANDSKRONA",
                "category": "Sofas & armchairs",
                "price": 8495.0,
                "designer": "IKEA of Sweden/Tord Bj\u00f6rklund",
                "rooms": "Living room, Bedroom"
            },
            "explanation": {
                "reason": "This recommended item is 89.06% similar to 4 items in your basket.",
                "similar_items": [
                    {
                        "name": "EKEDALEN / HENRIKSDAL",
                        "category": "Tables & desks",
                        "price": 4565.0
                    },
                    {
                        "name": "HAVSTA",
                        "category": "Cabinets & cupboards",
                        "price": 4580.0
                    },
                    {
                        "name": "LIDHULT",
                        "category": "Sofas & armchairs",
                        "price": 5428.0
                    },
                    {
                        "name": "LIDHULT",
                        "category": "Sofas & armchairs",
                        "price": 7748.0
                    }
                ]
            },
            "additional_info": {
                "average_price_in_cluster": 925.53,
                "designer_average_price": 2562.5
            }
        },
        {
            "recommended_item": {
                "item_id": 59256579,
                "name": "GR\u00d6NLID",
                "category": "Sofas & armchairs",
                "price": 7400.0,
                "designer": "Francis Cayouette",
                "rooms": "Living room, Bedroom"
            },
            "explanation": {
                "reason": "This recommended item is 88.43% similar to 4 items in your basket.",
                "similar_items": [
                    {
                        "name": "EKEDALEN / HENRIKSDAL",
                        "category": "Tables & desks",
                        "price": 4565.0
                    },
                    {
                        "name": "HAVSTA",
                        "category": "Cabinets & cupboards",
                        "price": 4580.0
                    },
                    {
                        "name": "LIDHULT",
                        "category": "Sofas & armchairs",
                        "price": 5428.0
                    },
                    {
                        "name": "LIDHULT",
                        "category": "Sofas & armchairs",
                        "price": 7748.0
                    }
                ]
            },
            "additional_info": {
                "average_price_in_cluster": 1262.61,
                "designer_average_price": 1124.69
            }
        },
        {
            "recommended_item": {
                "item_id": 89278612,
                "name": "GR\u00d6NLID",
                "category": "Sofas & armchairs, Beds",
                "price": 7610.0,
                "designer": "IKEA of Sweden/Ehl\u00e9n Johansson/Francis Cayouette",
                "rooms": "Living room, Bedroom"
            },
            "explanation": {
                "reason": "This recommended item is 88.35% similar to 4 items in your basket.",
                "similar_items": [
                    {
                        "name": "EKEDALEN / HENRIKSDAL",
                        "category": "Tables & desks",
                        "price": 4565.0
                    },
                    {
                        "name": "HAVSTA",
                        "category": "Cabinets & cupboards",
                        "price": 4580.0
                    },
                    {
                        "name": "LIDHULT",
                        "category": "Sofas & armchairs",
                        "price": 5428.0
                    },
                    {
                        "name": "LIDHULT",
                        "category": "Sofas & armchairs",
                        "price": 7748.0
                    }
                ]
            },
            "additional_info": {
                "average_price_in_cluster": 1262.61,
                "designer_average_price": 5331.67
            }
        },
        {
            "recommended_item": {
                "item_id": 89239748,
                "name": "NORSBORG",
                "category": "Sofas & armchairs",
                "price": 6780.0,
                "designer": "Ehl\u00e9n Johansson",
                "rooms": "Living room, Bedroom"
            },
            "explanation": {
                "reason": "This recommended item is 87.84% similar to 4 items in your basket.",
                "similar_items": [
                    {
                        "name": "EKEDALEN / HENRIKSDAL",
                        "category": "Tables & desks",
                        "price": 4565.0
                    },
                    {
                        "name": "HAVSTA",
                        "category": "Cabinets & cupboards",
                        "price": 4580.0
                    },
                    {
                        "name": "LIDHULT",
                        "category": "Sofas & armchairs",
                        "price": 5428.0
                    },
                    {
                        "name": "LIDHULT",
                        "category": "Sofas & armchairs",
                        "price": 7748.0
                    }
                ]
            },
            "additional_info": {
                "average_price_in_cluster": 1262.61,
                "designer_average_price": 1722.66
            }
        },
        {
            "recommended_item": {
                "item_id": 80403154,
                "name": "VEDBO",
                "category": "Chairs",
                "price": 695.0,
                "designer": "Francis Cayouette",
                "rooms": "Living room, Office, Kitchen, Dining room"
            },
            "explanation": {
                "reason": "This recommended item is 98.81% similar to 3 items in your basket.",
                "similar_items": [
                    {
                        "name": "EKEDALEN / EKEDALEN",
                        "category": "Tables & desks",
                        "price": 1245.0
                    },
                    {
                        "name": "NORDKISA",
                        "category": "Tables & desks",
                        "price": 476.0
                    },
                    {
                        "name": "SYVDE",
                        "category": "Tables & desks",
                        "price": 595.0
                    }
                ]
            },
            "additional_info": {
                "average_price_in_cluster": 1026.95,
                "designer_average_price": 1124.69
            }
        },
        {
            "recommended_item": {
                "item_id": 40339004,
                "name": "NORR\u00c5KER",
                "category": "Tables & desks",
                "price": 595.0,
                "designer": "J Karlsson/N Karlsson",
                "rooms": "Living room, Office, Kitchen, Dining room"
            },
            "explanation": {
                "reason": "This recommended item is 98.77% similar to 3 items in your basket.",
                "similar_items": [
                    {
                        "name": "EKEDALEN / EKEDALEN",
                        "category": "Tables & desks",
                        "price": 1245.0
                    },
                    {
                        "name": "NORDKISA",
                        "category": "Tables & desks",
                        "price": 476.0
                    },
                    {
                        "name": "SYVDE",
                        "category": "Tables & desks",
                        "price": 595.0
                    }
                ]
            },
            "additional_info": {
                "average_price_in_cluster": 1026.95,
                "designer_average_price": 616.44
            }
        },
        {
            "recommended_item": {
                "item_id": 59047147,
                "name": "HILVER / GERTON",
                "category": "Tables & desks",
                "price": 665.0,
                "designer": "IKEA of Sweden/Chenyi Ke",
                "rooms": "Living room, Office, Kitchen, Dining room"
            },
            "explanation": {
                "reason": "This recommended item is 98.75% similar to 3 items in your basket.",
                "similar_items": [
                    {
                        "name": "EKEDALEN / EKEDALEN",
                        "category": "Tables & desks",
                        "price": 1245.0
                    },
                    {
                        "name": "NORDKISA",
                        "category": "Tables & desks",
                        "price": 476.0
                    },
                    {
                        "name": "SYVDE",
                        "category": "Tables & desks",
                        "price": 595.0
                    }
                ]
            },
            "additional_info": {
                "average_price_in_cluster": 1026.95,
                "designer_average_price": 555.0
            }
        },
        {
            "recommended_item": {
                "item_id": 30396655,
                "name": "HEMNES",
                "category": "Chairs",
                "price": 495.0,
                "designer": "T Christensen/K Legaard",
                "rooms": "Living room, Office, Kitchen, Dining room"
            },
            "explanation": {
                "reason": "This recommended item is 98.62% similar to 3 items in your basket.",
                "similar_items": [
                    {
                        "name": "EKEDALEN / EKEDALEN",
                        "category": "Tables & desks",
                        "price": 1245.0
                    },
                    {
                        "name": "NORDKISA",
                        "category": "Tables & desks",
                        "price": 476.0
                    },
                    {
                        "name": "SYVDE",
                        "category": "Tables & desks",
                        "price": 595.0
                    }
                ]
            },
            "additional_info": {
                "average_price_in_cluster": 1026.95,
                "designer_average_price": 440.0
            }
        },
        {
            "recommended_item": {
                "item_id": 59306268,
                "name": "LERHAMN",
                "category": "Tables & desks",
                "price": 589.0,
                "designer": "Nike Karlsson",
                "rooms": "Living room, Office, Kitchen, Dining room"
            },
            "explanation": {
                "reason": "This recommended item is 98.57% similar to 3 items in your basket.",
                "similar_items": [
                    {
                        "name": "EKEDALEN / EKEDALEN",
                        "category": "Tables & desks",
                        "price": 1245.0
                    },
                    {
                        "name": "NORDKISA",
                        "category": "Tables & desks",
                        "price": 476.0
                    },
                    {
                        "name": "SYVDE",
                        "category": "Tables & desks",
                        "price": 595.0
                    }
                ]
            },
            "additional_info": {
                "average_price_in_cluster": 1026.95,
                "designer_average_price": 625.36
            }
        },
        {
            "recommended_item": {
                "item_id": 40247207,
                "name": "DALSHULT",
                "category": "Tables & desks",
                "price": 575.0,
                "designer": "Wiebke Braasch",
                "rooms": "Living room, Office, Kitchen, Dining room"
            },
            "explanation": {
                "reason": "This recommended item is 98.55% similar to 3 items in your basket.",
                "similar_items": [
                    {
                        "name": "EKEDALEN / EKEDALEN",
                        "category": "Tables & desks",
                        "price": 1245.0
                    },
                    {
                        "name": "NORDKISA",
                        "category": "Tables & desks",
                        "price": 476.0
                    },
                    {
                        "name": "SYVDE",
                        "category": "Tables & desks",
                        "price": 595.0
                    }
                ]
            },
            "additional_info": {
                "average_price_in_cluster": 1026.95,
                "designer_average_price": 410.0
            }
        }
    ]
}